fabricatio_webui-0.1.2.dist-info/METADATA
fabricatio_webui-0.1.2.dist-info/WHEEL
fabricatio_webui-0.1.2.dist-info/entry_points.txt
fabricatio_webui/__init__.py
fabricatio_webui/actions/__init__.py
fabricatio_webui/capabilities/__init__.py
fabricatio_webui/cli.py
fabricatio_webui/config.py
fabricatio_webui/models/__init__.py
fabricatio_webui/py.typed
fabricatio_webui/rust.cpython-312-darwin.so
fabricatio_webui/rust.pyi
fabricatio_webui/workflows/__init__.py
fabricatio_webui/www/assets/AboutView-BFrzk1kX.js
fabricatio_webui/www/assets/AboutView-E68f7lAM.css
fabricatio_webui/www/assets/index-D6cKgIcX.js
fabricatio_webui/www/assets/index-DMb1Gf6K.css
fabricatio_webui/www/favicon.ico
fabricatio_webui/www/index.html
fabricatio_webui-0.1.2.dist-info/RECORD
