Metadata-Version: 2.4
Name: fabricatio-webui
Version: 0.1.2
Classifier: License :: OSI Approved :: MIT License
Classifier: Programming Language :: Python :: 3.12
Classifier: Programming Language :: Python :: 3.13
Classifier: Programming Language :: Python :: 3.14
Classifier: Programming Language :: Python :: Implementation :: CPython
Classifier: Typing :: Typed
Requires-Dist: fabricatio-core
Requires-Dist: typer-slim[standard]>=0.15.2 ; extra == 'cli'
Provides-Extra: cli
Summary: An extension of fabricatio
Author-email: Whth <zettainspector@foxmail.com>
License-Expression: MIT
Requires-Python: >=3.12, <3.15
Project-URL: Homepage, https://github.com/Whth/fabricatio
Project-URL: Repository, https://github.com/Whth/fabricatio
Project-URL: Issues, https://github.com/Whth/fabricatio/issues
